<?xml version="1.0" encoding="iso-8859-1"?>

	<metadata>
		<!-- details of each product -->
		<sitename name="localhost" siteId="1">      
      <title><![CDATA[Flowers delivered - FREE flower delivery uk. Flowers by post by online florists, send flowers next or same-day]]></title>
      <metakeywords><![CDATA[Flower flowers delivery delivered london online florist florists send flowers sending order ordering,bouquets, same day flowers]]></metakeywords>
      <metadescription><![CDATA[Best Flower Delivery Service 2011 according to Which magazine. FREE Flower Delivery, order by 8pm for next day delivery. 100% Satisfaction Guaranteed on flowers delivered.]]></metadescription>
		</sitename>
    <sitename name="94.199.190.106" siteId="13">
      <title><![CDATA[Plant Delivery UK | Plant gifts | Send plant gifts | Buy plants Online | On line plants]]></title>
      <metakeywords><![CDATA[buy plants online,plant gift, plants by post, send plant UK ,pot plants, send plant England, outdoor plants]]></metakeywords>
      <metadescription><![CDATA[Plant Delivery for UK next day delivery.]]></metadescription>
    </sitename>
    <sitename name="94.199.190.107" siteId="3">
      <title><![CDATA[Chocolate Gift Delivery UK | Truffle gifts | Send chocolate gifts | Buy dark and white chocolate Online | On line chocolate merchant]]></title>
      <metakeywords><![CDATA[chocolates by post, chocolates delivery,chocolate gifts, luxury chocolate gifts, luxury chocolates,chocolate Christmas Gifts, chocolate gifts]]></metakeywords>
      <metadescription><![CDATA[Chocolate Gift Delivery for UK next day delivery.]]></metadescription>
    </sitename>
    <sitename name="94.199.190.108" siteId="6">
    <title><![CDATA[Hamper Gift Delivery UK | Hamper gifts | Send hamper gifts | Buy hampers Online | On line hampers]]></title>
      <metakeywords><![CDATA[Flowers]]></metakeywords>
    <metadescription><![CDATA[Flowers]]></metadescription>
  </sitename>
	</metadata>





